[
  {
    "BGART" : "",
    "BGART_SMALL" : "",
    "Developer" : "Coleco",
    "NA" : "1977",
    "Publisher" : "Coleco",
    "Title" : "Cartridge 1: Road Race, Tennis, Quickdraw"
  },
  {
    "BGART" : "",
    "BGART_SMALL" : "",
    "Developer" : "Coleco",
    "NA" : "1977",
    "Publisher" : "Coleco",
    "Title" : "Cartridge 2: Hockey, Tennis, Handball, Target"
  },
  {
    "BGART" : "",
    "BGART_SMALL" : "",
    "Developer" : "Coleco",
    "NA" : "1977",
    "Publisher" : "Coleco",
    "Title" : "Cartridge 3: Bouns Pinball, Shooting Gallery, Shoot the Bear, Deluxe Pinball"
  },
  {
    "BGART" : "",
    "BGART_SMALL" : "",
    "Developer" : "Coleco",
    "NA" : "1977",
    "Publisher" : "Coleco",
    "Title" : "Cartridge 4: Naval Battle, Blast Away, Speedball"
  }
]